jain/__init__.py
jain/jain_module.py
jain-8.24.1.dist-info/LICENSE
jain-8.24.1.dist-info/METADATA
jain-8.24.1.dist-info/WHEEL
jain-8.24.1.dist-info/top_level.txt
jain-8.24.1.dist-info/RECORD
