Metadata-Version: 2.1
Name: jain
Version: 8.24.1
Summary: A package
Author-email: Rajeev Jain <rajeeja@gmail.com>
License: MIT
Classifier: Programming Language :: Python :: 3
Classifier: License :: OSI Approved :: MIT License
Classifier: Operating System :: OS Independent
License-File: LICENSE
Requires-Dist: requests
